crysp/__init__.py
crysp/aes.py
crysp/bits.py
crysp/blake.py
crysp/chacha.py
crysp/crc.py
crysp/des.py
crysp/hmac.py
crysp/keccak.py
crysp/md.py
crysp/mode.py
crysp/nilsimsa.py
crysp/padding.py
crysp/poly.py
crysp/rc4.py
crysp/salsa20.py
crysp/serpent.py
crysp/sha.py
crysp/skein.py
crysp/threefish.py
crysp/tlsh.py
crysp/wb.py
crysp/utils/__init__.py
crysp/utils/freq1.py
crysp/utils/freq2.py
crysp/utils/freq3.py
crysp/utils/knapsack.py
crysp/utils/oldies.py
crysp/utils/operators.py
crysp/utils/perms.py
crysp/utils/words.py
crysp-1.1.dist-info/LICENSE
crysp-1.1.dist-info/METADATA
crysp-1.1.dist-info/WHEEL
crysp-1.1.dist-info/top_level.txt
crysp-1.1.dist-info/RECORD
